improved_fmmds_core/__init__.py
improved_fmmds_core/algorithms.py
improved_fmmds_core/constraints.py
improved_fmmds_core/cli/__init__.py
improved_fmmds_core/cli/main.py
improved_fmmds_core/parallel/__init__.py
improved_fmmds_core/parallel/cython_utils.cpp
improved_fmmds_core/parallel/cython_utils.cpython-310-darwin.so
improved_fmmds_core/parallel/cython_utils.pyx
improved_fmmds_core-1.0.0.dist-info/licenses/LICENSE
improved_fmmds_core-1.0.0.dist-info/METADATA
improved_fmmds_core-1.0.0.dist-info/WHEEL
improved_fmmds_core-1.0.0.dist-info/entry_points.txt
improved_fmmds_core-1.0.0.dist-info/top_level.txt
improved_fmmds_core-1.0.0.dist-info/RECORD
