Metadata-Version: 2.4
Name: improved-fmmds-core
Version: 1.0.0
Summary: Core implementation of the Improved FMMD-S algorithm for fair max-min diversification
Author-email: Ananth Mahadevan <ananth.mahadevan@helsinki.fi>
License: MIT License
Keywords: fairness,diversification,optimization,clustering,sampling
Requires-Python: >=3.8
License-File: LICENSE
Requires-Dist: numpy>=1.20.0
Requires-Dist: gurobipy>=9.0.0
Requires-Dist: networkx>=2.5
Requires-Dist: tqdm>=4.60.0
Requires-Dist: cython>=0.29.0
Dynamic: license-file
